{
  "apiKey": "********************************",
  "to": "****@**.**",
  "toName": "********************************",
  "from": "****@**.**",
  "fromName": "********************************",
  "replyTo": "****@**.**",
  "replyToName": "********************************",
  "subject": "********************************",
  "message": 0,
  "domain": "***.**",
  "campaignId": 0,
  "plain_text": "plain text",
  "replace": {
    "KEY": "VALUE"
  },
  "merges": {
    "merge_1": "VALUE"
  },
  "list_id": 0
}
